mets_mods2tei/__init__.py
mets_mods2tei/api/__init__.py
mets_mods2tei/api/alto.py
mets_mods2tei/api/mets.py
mets_mods2tei/api/mets_generateds.py
mets_mods2tei/api/mods_generateds.py
mets_mods2tei/api/tei.py
mets_mods2tei/api/util.py
mets_mods2tei/data/iso15924-utf8-20180827.txt
mets_mods2tei/data/tei_skeleton.xml
mets_mods2tei/scripts/__init__.py
mets_mods2tei/scripts/mets_mods2tei.py
mets_mods2tei/scripts/update.py
mets_mods2tei-0.1.5.dist-info/LICENSE
mets_mods2tei-0.1.5.dist-info/METADATA
mets_mods2tei-0.1.5.dist-info/WHEEL
mets_mods2tei-0.1.5.dist-info/entry_points.txt
mets_mods2tei-0.1.5.dist-info/top_level.txt
mets_mods2tei-0.1.5.dist-info/RECORD
