Metadata-Version: 2.1
Name: mets-mods2tei
Version: 0.1.5
Summary: Convert digital documents in METS/MODS format to TEI
Author: Kay-Michael Würzner
Author-email: kay-michael.wuerzner@slub-dresden.de
Classifier: Development Status :: 5 - Production/Stable
Classifier: Environment :: Console
Classifier: Intended Audience :: Developers
Classifier: Intended Audience :: Education
Classifier: Intended Audience :: Information Technology
Classifier: Intended Audience :: Science/Research
Classifier: License :: OSI Approved :: GNU General Public License v3 (GPLv3)
Classifier: Programming Language :: Python
Classifier: Topic :: Text Processing :: Markup :: XML
Requires-Python: >=3.7
License-File: LICENSE
Requires-Dist: click
Requires-Dist: lxml
Requires-Dist: babel
Requires-Dist: generateDS
Requires-Dist: rapidfuzz
Requires-Dist: more-itertools
Requires-Dist: ocrd (>=2.59)
Requires-Dist: importlib-resources ; python_version < "3.10"
